Workbook

Sheet Raw_EUR
A1: Raw CFTC data, euro FX futures, positions as of each Tuesday
A2: Source: CFTC Traders in Financial Futures, Futures Only, EURO FX - CHICAGO MERCANTILE EXCHANGE (code 099741, contract of EUR 125,000). https://publicreporting.cftc.gov/Commitments-of-Traders/Traders-in-Financial-Futures-Futures-Only/gpe5-46if . Accessed 19 Oct 2026. Data used: positions up to Tue 1 Sep 2026 (released Fri 4 Sep 2026).
A3: Blue = value copied from the CFTC file. Long and short are outright positions; spreading is excluded. Nonreportable entries for 16 Jun look unusual as published (both long and short more than doubled); they are not used in the report.
A4: Positions as of (Tuesday) | B4: Open interest | C4: Dealer long | D4: Dealer short | E4: Asset manager long | F4: Asset manager short | G4: Leveraged funds long | H4: Leveraged funds short | I4: Other reportable long | J4: Other reportable short | K4: Nonreportable long | L4: Nonreportable short
A5: 46175 | B5: 842424 | C5: 45480 | D5: 374951 | E5: 454078 | F5: 168157 | G5: 109583 | H5: 97556 | I5: 25388 | J5: 14395 | K5: 86539 | L5: 66009
A6: 46182 | B6: 871507 | C6: 67752 | D6: 367097 | E6: 462310 | F6: 180754 | G6: 91856 | H6: 109244 | I6: 25497 | J6: 14473 | K6: 90399 | L6: 66246
A7: 46189 | B7: 894671 | C7: 32449 | D7: 331417 | E7: 460022 | F7: 189678 | G7: 94228 | H7: 103154 | I7: 23796 | J7: 13782 | K7: 214087 | L7: 186551
A8: 46196 | B8: 785477 | C8: 36965 | D8: 312295 | E8: 462293 | F8: 207563 | G8: 108150 | H8: 123560 | I8: 22501 | J8: 13516 | K8: 81337 | L8: 54312
A9: 46203 | B9: 790076 | C9: 39903 | D9: 293368 | E9: 470602 | F9: 215444 | G9: 102267 | H9: 134911 | I9: 20919 | J9: 13548 | K9: 80468 | L9: 56888
A10: 46210 | B10: 794833 | C10: 43012 | D10: 289135 | E10: 478070 | F10: 224152 | G10: 87460 | H10: 132921 | I10: 22853 | J10: 11438 | K10: 83533 | L10: 57282
A11: 46217 | B11: 799495 | C11: 45006 | D11: 277174 | E11: 466709 | F11: 219393 | G11: 89976 | H11: 143667 | I11: 23465 | J11: 10917 | K11: 82849 | L11: 56854
A12: 46224 | B12: 800061 | C12: 51686 | D12: 259905 | E12: 458394 | F12: 229467 | G12: 91110 | H12: 147781 | I12: 23901 | J12: 11301 | K12: 80473 | L12: 57110
A13: 46231 | B13: 819806 | C13: 76674 | D13: 252190 | E13: 449191 | F13: 239865 | G13: 92672 | H13: 157870 | I13: 23041 | J13: 12386 | K13: 78549 | L13: 57816
A14: 46238 | B14: 799909 | C14: 51250 | D14: 255728 | E14: 445903 | F14: 226641 | G14: 95389 | H14: 147594 | I14: 22715 | J14: 11923 | K14: 80953 | L14: 54324
A15: 46245 | B15: 801884 | C15: 53721 | D15: 259757 | E15: 450831 | F15: 225442 | G15: 86753 | H15: 147353 | I15: 23277 | J15: 12837 | K15: 82886 | L15: 52079
A16: 46252 | B16: 804940 | C16: 53199 | D16: 277471 | E16: 451575 | F16: 214149 | G16: 90140 | H16: 147856 | I16: 24290 | J16: 14761 | K16: 86443 | L16: 51410
... A18: 46266 | B18: 865412 | C18: 54643 | D18: 322221 | E18: 468254 | F18: 205001 | G18: 96137 | H18: 134310 | I18: 23850 | J18: 15004 | K18: 85670 | L18: 52018

Sheet Net_EUR
A1: Euro: net position by trader category, week on week change, net as % of open interest
A2: Source: CFTC, as on Raw_EUR. Accessed 19 Oct 2026. Data used: positions up to Tue 1 Sep 2026 (released Fri 4 Sep 2026).
A3: All cells are formulas on Raw_EUR. Net = long minus short. WoW = change from the previous Tuesday (the first row has no prior week in this file). Net % OI = net divided by open interest. Shaded: 1 Sep, the latest print.
A4: Positions as of (Tuesday) | B4: Open interest | C4: Leveraged funds net | D4: Leveraged funds net WoW | E4: Leveraged funds net % OI | F4: Asset manager net | G4: Asset manager net WoW | H4: Asset manager net % OI | I4: Dealer net | J4: Dealer net WoW | K4: Dealer net % OI | L4: Other reportable net | M4: Other reportable net WoW | N4: Other reportable net % OI | O4: Nonreportable net | P4: Nonreportable net WoW | Q4: Nonreportable net % OI
A5: =Raw_EUR!A5 -> 46175 | B5: =Raw_EUR!B5 -> 842424 | C5: =Raw_EUR!G5-Raw_EUR!H5 -> 12027 | D5: n/a | E5: =C5/B5 -> 0.014276659 | F5: =Raw_EUR!E5-Raw_EUR!F5 -> 285921 | G5: n/a | H5: =F5/B5 -> 0.33940272 | I5: =Raw_EUR!C5-Raw_EUR!D5 -> -329471 | J5: n/a | K5: =I5/B5 -> -0.39109878 | L5: =Raw_EUR!I5-Raw_EUR!J5 -> 10993 | M5: n/a | N5: =L5/B5 -> 0.013049248 | O5: =Raw_EUR!K5-Raw_EUR!L5 -> 20530 | P5: n/a | Q5: =O5/B5 -> 0.024370151
A6: =Raw_EUR!A6 -> 46182 | B6: =Raw_EUR!B6 -> 871507 | C6: =Raw_EUR!G6-Raw_EUR!H6 -> -17388 | D6: =C6-C5 -> -29415 | E6: =C6/B6 -> -0.019951647 | F6: =Raw_EUR!E6-Raw_EUR!F6 -> 281556 | G6: =F6-F5 -> -4365 | H6: =F6/B6 -> 0.32306797 | I6: =Raw_EUR!C6-Raw_EUR!D6 -> -299345 | J6: =I6-I5 -> 30126 | K6: =I6/B6 -> -0.34347974 | L6: =Raw_EUR!I6-Raw_EUR!J6 -> 11024 | M6: =L6-L5 -> 31 | N6: =L6/B6 -> 0.012649353 | O6: =Raw_EUR!K6-Raw_EUR!L6 -> 24153 | P6: =O6-O5 -> 3623 | Q6: =O6/B6 -> 0.027714063
A7: =Raw_EUR!A7 -> 46189 | B7: =Raw_EUR!B7 -> 894671 | C7: =Raw_EUR!G7-Raw_EUR!H7 -> -8926 | D7: =C7-C6 -> 8462 | E7: =C7/B7 -> -0.0099768518 | F7: =Raw_EUR!E7-Raw_EUR!F7 -> 270344 | G7: =F7-F6 -> -11212 | H7: =F7/B7 -> 0.30217141 | I7: =Raw_EUR!C7-Raw_EUR!D7 -> -298968 | J7: =I7-I6 -> 377 | K7: =I7/B7 -> -0.3341653 | L7: =Raw_EUR!I7-Raw_EUR!J7 -> 10014 | M7: =L7-L6 -> -1010 | N7: =L7/B7 -> 0.011192941 | O7: =Raw_EUR!K7-Raw_EUR!L7 -> 27536 | P7: =O7-O6 -> 3383 | Q7: =O7/B7 -> 0.030777794
A8: =Raw_EUR!A8 -> 46196 | B8: =Raw_EUR!B8 -> 785477 | C8: =Raw_EUR!G8-Raw_EUR!H8 -> -15410 | D8: =C8-C7 -> -6484 | E8: =C8/B8 -> -0.019618652 | F8: =Raw_EUR!E8-Raw_EUR!F8 -> 254730 | G8: =F8-F7 -> -15614 | H8: =F8/B8 -> 0.32429976 | I8: =Raw_EUR!C8-Raw_EUR!D8 -> -275330 | J8: =I8-I7 -> 23638 | K8: =I8/B8 -> -0.35052586 | L8: =Raw_EUR!I8-Raw_EUR!J8 -> 8985 | M8: =L8-L7 -> -1029 | N8: =L8/B8 -> 0.011438909 | O8: =Raw_EUR!K8-Raw_EUR!L8 -> 27025 | P8: =O8-O7 -> -511 | Q8: =O8/B8 -> 0.034405845
A9: =Raw_EUR!A9 -> 46203 | B9: =Raw_EUR!B9 -> 790076 | C9: =Raw_EUR!G9-Raw_EUR!H9 -> -32644 | D9: =C9-C8 -> -17234 | E9: =C9/B9 -> -0.041317544 | F9: =Raw_EUR!E9-Raw_EUR!F9 -> 255158 | G9: =F9-F8 -> 428 | H9: =F9/B9 -> 0.32295374 | I9: =Raw_EUR!C9-Raw_EUR!D9 -> -253465 | J9: =I9-I8 -> 21865 | K9: =I9/B9 -> -0.32081091 | L9: =Raw_EUR!I9-Raw_EUR!J9 -> 7371 | M9: =L9-L8 -> -1614 | N9: =L9/B9 -> 0.0093294822 | O9: =Raw_EUR!K9-Raw_EUR!L9 -> 23580 | P9: =O9-O8 -> -3445 | Q9: =O9/B9 -> 0.02984523
A10: =Raw_EUR!A10 -> 46210 | B10: =Raw_EUR!B10 -> 794833 | C10: =Raw_EUR!G10-Raw_EUR!H10 -> -45461 | D10: =C10-C9 -> -12817 | E10: =C10/B10 -> -0.057195662 | F10: =Raw_EUR!E10-Raw_EUR!F10 -> 253918 | G10: =F10-F9 -> -1240 | H10: =F10/B10 -> 0.31946082 | I10: =Raw_EUR!C10-Raw_EUR!D10 -> -246123 | J10: =I10-I9 -> 7342 | K10: =I10/B10 -> -0.30965373 | L10: =Raw_EUR!I10-Raw_EUR!J10 -> 11415 | M10: =L10-L9 -> 4044 | N10: =L10/B10 -> 0.014361507 | O10: =Raw_EUR!K10-Raw_EUR!L10 -> 26251 | P10: =O10-O9 -> 2671 | Q10: =O10/B10 -> 0.033027064
A11: =Raw_EUR!A11 -> 46217 | B11: =Raw_EUR!B11 -> 799495 | C11: =Raw_EUR!G11-Raw_EUR!H11 -> -53691 | D11: =C11-C10 -> -8230 | E11: =C11/B11 -> -0.067156142 | F11: =Raw_EUR!E11-Raw_EUR!F11 -> 247316 | G11: =F11-F10 -> -6602 | H11: =F11/B11 -> 0.30934027 | I11: =Raw_EUR!C11-Raw_EUR!D11 -> -232168 | J11: =I11-I10 -> 13955 | K11: =I11/B11 -> -0.29039331 | L11: =Raw_EUR!I11-Raw_EUR!J11 -> 12548 | M11: =L11-L10 -> 1133 | N11: =L11/B11 -> 0.015694907 | O11: =Raw_EUR!K11-Raw_EUR!L11 -> 25995 | P11: =O11-O10 -> -256 | Q11: =O11/B11 -> 0.032514275
A12: =Raw_EUR!A12 -> 46224 | B12: =Raw_EUR!B12 -> 800061 | C12: =Raw_EUR!G12-Raw_EUR!H12 -> -56671 | D12: =C12-C11 -> -2980 | E12: =C12/B12 -> -0.070833349 | F12: =Raw_EUR!E12-Raw_EUR!F12 -> 228927 | G12: =F12-F11 -> -18389 | H12: =F12/B12 -> 0.28613693 | I12: =Raw_EUR!C12-Raw_EUR!D12 -> -208219 | J12: =I12-I11 -> 23949 | K12: =I12/B12 -> -0.26025391 | L12: =Raw_EUR!I12-Raw_EUR!J12 -> 12600 | M12: =L12-L11 -> 52 | N12: =L12/B12 -> 0.015748799 | O12: =Raw_EUR!K12-Raw_EUR!L12 -> 23363 | P12: =O12-O11 -> -2632 | Q12: =O12/B12 -> 0.029201523
A13: =Raw_EUR!A13 -> 46231 | B13: =Raw_EUR!B13 -> 819806 | C13: =Raw_EUR!G13-Raw_EUR!H13 -> -65198 | D13: =C13-C12 -> -8527 | E13: =C13/B13 -> -0.079528571 | F13: =Raw_EUR!E13-Raw_EUR!F13 -> 209326 | G13: =F13-F12 -> -19601 | H13: =F13/B13 -> 0.25533602 | I13: =Raw_EUR!C13-Raw_EUR!D13 -> -175516 | J13: =I13-I12 -> 32703 | K13: =I13/B13 -> -0.21409455 | L13: =Raw_EUR!I13-Raw_EUR!J13 -> 10655 | M13: =L13-L12 -> -1945 | N13: =L13/B13 -> 0.012996977 | O13: =Raw_EUR!K13-Raw_EUR!L13 -> 20733 | P13: =O13-O12 -> -2630 | Q13: =O13/B13 -> 0.02529013
A14: =Raw_EUR!A14 -> 46238 | B14: =Raw_EUR!B14 -> 799909 | C14: =Raw_EUR!G14-Raw_EUR!H14 -> -52205 | D14: =C14-C13 -> 12993 | E14: =C14/B14 -> -0.065263674 | F14: =Raw_EUR!E14-Raw_EUR!F14 -> 219262 | G14: =F14-F13 -> 9936 | H14: =F14/B14 -> 0.27410868 | I14: =Raw_EUR!C14-Raw_EUR!D14 -> -204478 | J14: =I14-I13 -> -28962 | K14: =I14/B14 -> -0.25562658 | L14: =Raw_EUR!I14-Raw_EUR!J14 -> 10792 | M14: =L14-L13 -> 137 | N14: =L14/B14 -> 0.013491535 | O14: =Raw_EUR!K14-Raw_EUR!L14 -> 26629 | P14: =O14-O13 -> 5896 | Q14: =O14/B14 -> 0.033290037
A15: =Raw_EUR!A15 -> 46245 | B15: =Raw_EUR!B15 -> 801884 | C15: =Raw_EUR!G15-Raw_EUR!H15 -> -60600 | D15: =C15-C14 -> -8395 | E15: =C15/B15 -> -0.075572028 | F15: =Raw_EUR!E15-Raw_EUR!F15 -> 225389 | G15: =F15-F14 -> 6127 | H15: =F15/B15 -> 0.28107432 | I15: =Raw_EUR!C15-Raw_EUR!D15 -> -206036 | J15: =I15-I14 -> -1558 | K15: =I15/B15 -> -0.25693991 | L15: =Raw_EUR!I15-Raw_EUR!J15 -> 10440 | M15: =L15-L14 -> -352 | N15: =L15/B15 -> 0.013019339 | O15: =Raw_EUR!K15-Raw_EUR!L15 -> 30807 | P15: =O15-O14 -> 4178 | Q15: =O15/B15 -> 0.038418275
A16: =Raw_EUR!A16 -> 46252 | B16: =Raw_EUR!B16 -> 804940 | C16: =Raw_EUR!G16-Raw_EUR!H16 -> -57716 | D16: =C16-C15 -> 2884 | E16: =C16/B16 -> -0.071702239 | F16: =Raw_EUR!E16-Raw_EUR!F16 -> 237426 | G16: =F16-F15 -> 12037 | H16: =F16/B16 -> 0.29496112 | I16: =Raw_EUR!C16-Raw_EUR!D16 -> -224272 | J16: =I16-I15 -> -18236 | K16: =I16/B16 -> -0.27861952 | L16: =Raw_EUR!I16-Raw_EUR!J16 -> 9529 | M16: =L16-L15 -> -911 | N16: =L16/B16 -> 0.011838149 | O16: =Raw_EUR!K16-Raw_EUR!L16 -> 35033 | P16: =O16-O15 -> 4226 | Q16: =O16/B16 -> 0.043522499
A17: =Raw_EUR!A17 -> 46259 | B17: =Raw_EUR!B17 -> 818524 | C17: =Raw_EUR!G17-Raw_EUR!H17 -> -38359 | D17: =C17-C16 -> 19357 | E17: =C17/B17 -> -0.046863623 | F17: =Raw_EUR!E17-Raw_EUR!F17 -> 261426 | G17: =F17-F16 -> 24000 | H17: =F17/B17 -> 0.31938709 | I17: =Raw_EUR!C17-Raw_EUR!D17 -> -268581 | J17: =I17-I16 -> -44309 | K17: =I17/B17 -> -0.32812844 | L17: =Raw_EUR!I17-Raw_EUR!J17 -> 9602 | M17: =L17-L16 -> 73 | N17: =L17/B17 -> 0.011730872 | O17: =Raw_EUR!K17-Raw_EUR!L17 -> 35912 | P17: =O17-O16 -> 879 | Q17: =O17/B17 -> 0.043874095
A18: =Raw_EUR!A18 -> 46266 | B18: =Raw_EUR!B18 -> 865412 | C18: =Raw_EUR!G18-Raw_EUR!H18 -> -38173 | D18: =C18-C17 -> 186 | E18: =C18/B18 -> -0.044109626 | F18: =Raw_EUR!E18-Raw_EUR!F18 -> 263253 | G18: =F18-F17 -> 1827 | H18: =F18/B18 -> 0.30419384 | I18: =Raw_EUR!C18-Raw_EUR!D18 -> -267578 | J18: =I18-I17 -> 1003 | K18: =I18/B18 -> -0.30919146 | L18: =Raw_EUR!I18-Raw_EUR!J18 -> 8846 | M18: =L18-L17 -> -756 | N18: =L18/B18 -> 0.010221721 | O18: =Raw_EUR!K18-Raw_EUR!L18 -> 33652 | P18: =O18-O17 -> -2260 | Q18: =O18/B18 -> 0.038885525

Sheet Raw_Other_FX
A1: Raw CFTC data, other currency futures, leveraged funds, positions as of Tue 25 Aug and Tue 1 Sep 2026
A2: Source: CFTC Traders in Financial Futures, Futures Only, CME contracts. https://publicreporting.cftc.gov/Commitments-of-Traders/Traders-in-Financial-Futures-Futures-Only/gpe5-46if . Accessed 19 Oct 2026. Data used: positions up to Tue 1 Sep 2026 (released Fri 4 Sep 2026).
A3: Blue = value copied from the CFTC file. Contract sizes differ by currency, so compare currencies on net % of open interest, not on contract counts.
A4: Currency | B4: Code | C4: CFTC market code | D4: Contract size | E4: Positions as of (Tuesday) | F4: Open interest | G4: Leveraged funds long | H4: Leveraged funds short
A5: British pound | B5: GBP | C5: 096742 | D5: GBP 62,500 | E5: 46259 | F5: 318468 | G5: 81286 | H5: 33377
A6: British pound | B6: GBP | C6: 096742 | D6: GBP 62,500 | E6: 46266 | F6: 317961 | G6: 77117 | H6: 33950
A7: Japanese yen | B7: JPY | C7: 097741 | D7: JPY 12,500,000 | E7: 46259 | F7: 384216 | G7: 66528 | H7: 143570
A8: Japanese yen | B8: JPY | C8: 097741 | D8: JPY 12,500,000 | E8: 46266 | F8: 411882 | G8: 58529 | H8: 160717
A9: Swiss franc | B9: CHF | C9: 092741 | D9: CHF 125,000 | E9: 46259 | F9: 108923 | G9: 12353 | H9: 21178
A10: Swiss franc | B10: CHF | C10: 092741 | D10: CHF 125,000 | E10: 46266 | F10: 136962 | G10: 12305 | H10: 22603
A11: Canadian dollar | B11: CAD | C11: 090741 | D11: CAD 100,000 | E11: 46259 | F11: 329544 | G11: 27384 | H11: 99476
A12: Canadian dollar | B12: CAD | C12: 090741 | D12: CAD 100,000 | E12: 46266 | F12: 334800 | G12: 27845 | H12: 96595
A13: Australian dollar | B13: AUD | C13: 232741 | D13: AUD 100,000 | E13: 46259 | F13: 333906 | G13: 81344 | H13: 27283
A14: Australian dollar | B14: AUD | C14: 232741 | D14: AUD 100,000 | E14: 46266 | F14: 391678 | G14: 78498 | H14: 28836
A15: New Zealand dollar | B15: NZD | C15: 112741 | D15: NZD 100,000 | E15: 46259 | F15: 88964 | G15: 3673 | H15: 35667
A16: New Zealand dollar | B16: NZD | C16: 112741 | D16: NZD 100,000 | E16: 46266 | F16: 107274 | G16: 5216 | H16: 27554

Sheet FX_Context
A1: Leveraged funds net position, major currencies, 1 Sep 2026 with week on week change
A2: Source: CFTC, as on Raw_EUR and Raw_Other_FX. Accessed 19 Oct 2026. Data used: positions up to Tue 1 Sep 2026 (released Fri 4 Sep 2026).
A3: All cells are formulas. Net = long minus short. WoW = 1 Sep net minus 25 Aug net. Net % OI = net divided by open interest.
A4: Currency | B4: Leveraged funds long, 1 Sep | C4: Leveraged funds short, 1 Sep | D4: Net, 1 Sep | E4: Net, 25 Aug | F4: Net WoW | G4: Open interest, 1 Sep | H4: Net % OI, 1 Sep | I4: Net % OI, 25 Aug
A5: Euro (EUR) | B5: =Raw_EUR!G18 -> 96137 | C5: =Raw_EUR!H18 -> 134310 | D5: =B5-C5 -> -38173 | E5: =Raw_EUR!G17-Raw_EUR!H17 -> -38359 | F5: =D5-E5 -> 186 | G5: =Raw_EUR!B18 -> 865412 | H5: =D5/G5 -> -0.044109626 | I5: =E5/Raw_EUR!B17 -> -0.046863623
A6: British pound (GBP) | B6: =Raw_Other_FX!G6 -> 77117 | C6: =Raw_Other_FX!H6 -> 33950 | D6: =B6-C6 -> 43167 | E6: =Raw_Other_FX!G5-Raw_Other_FX!H5 -> 47909 | F6: =D6-E6 -> -4742 | G6: =Raw_Other_FX!F6 -> 317961 | H6: =D6/G6 -> 0.13576193 | I6: =E6/Raw_Other_FX!F5 -> 0.15043584
A7: Japanese yen (JPY) | B7: =Raw_Other_FX!G8 -> 58529 | C7: =Raw_Other_FX!H8 -> 160717 | D7: =B7-C7 -> -102188 | E7: =Raw_Other_FX!G7-Raw_Other_FX!H7 -> -77042 | F7: =D7-E7 -> -25146 | G7: =Raw_Other_FX!F8 -> 411882 | H7: =D7/G7 -> -0.24810018 | I7: =E7/Raw_Other_FX!F7 -> -0.20051742
A8: Swiss franc (CHF) | B8: =Raw_Other_FX!G10 -> 12305 | C8: =Raw_Other_FX!H10 -> 22603 | D8: =B8-C8 -> -10298 | E8: =Raw_Other_FX!G9-Raw_Other_FX!H9 -> -8825 | F8: =D8-E8 -> -1473 | G8: =Raw_Other_FX!F10 -> 136962 | H8: =D8/G8 -> -0.075188738 | I8: =E8/Raw_Other_FX!F9 -> -0.081020537
A9: Canadian dollar (CAD) | B9: =Raw_Other_FX!G12 -> 27845 | C9: =Raw_Other_FX!H12 -> 96595 | D9: =B9-C9 -> -68750 | E9: =Raw_Other_FX!G11-Raw_Other_FX!H11 -> -72092 | F9: =D9-E9 -> 3342 | G9: =Raw_Other_FX!F12 -> 334800 | H9: =D9/G9 -> -0.20534648 | I9: =E9/Raw_Other_FX!F11 -> -0.2187629
A10: Australian dollar (AUD) | B10: =Raw_Other_FX!G14 -> 78498 | C10: =Raw_Other_FX!H14 -> 28836 | D10: =B10-C10 -> 49662 | E10: =Raw_Other_FX!G13-Raw_Other_FX!H13 -> 54061 | F10: =D10-E10 -> -4399 | G10: =Raw_Other_FX!F14 -> 391678 | H10: =D10/G10 -> 0.12679293 | I10: =E10/Raw_Other_FX!F13 -> 0.16190485
A11: New Zealand dollar (NZD) | B11: =Raw_Other_FX!G16 -> 5216 | C11: =Raw_Other_FX!H16 -> 27554 | D11: =B11-C11 -> -22338 | E11: =Raw_Other_FX!G15-Raw_Other_FX!H15 -> -31994 | F11: =D11-E11 -> 9656 | G11: =Raw_Other_FX!F16 -> 107274 | H11: =D11/G11 -> -0.20823312 | I11: =E11/Raw_Other_FX!F15 -> -0.35962861

Sheet Summary
A1: Summary: euro leveraged funds going into the ECB decision of Thu 10 Sep 2026
A2: Source: CFTC, as on Raw_EUR. Accessed 19 Oct 2026. Data used: positions up to Tue 1 Sep 2026 (released Fri 4 Sep 2026).
A3: All cells are formulas on Net_EUR and Raw_EUR.
A5: Leveraged funds, euro FX | B5: 25 Aug 2026 | C5: 1 Sep 2026 | D5: Change
A6: Long contracts | B6: =Raw_EUR!G17 -> 90921 | C6: =Raw_EUR!G18 -> 96137 | D6: =C6-B6 -> 5216
A7: Short contracts | B7: =Raw_EUR!H17 -> 129280 | C7: =Raw_EUR!H18 -> 134310 | D7: =C7-B7 -> 5030
A8: Net position | B8: =Net_EUR!C17 -> -38359 | C8: =Net_EUR!C18 -> -38173 | D8: =C8-B8 -> 186
A9: Open interest | B9: =Raw_EUR!B17 -> 818524 | C9: =Raw_EUR!B18 -> 865412 | D9: =C9-B9 -> 46888
A10: Net % of open interest | B10: =Net_EUR!E17 -> -0.046863623 | C10: =Net_EUR!E18 -> -0.044109626 | D10: =C10-B10 -> 0.0027539964
A12: Net position by category, 1 Sep
A13: Category | B13: 25 Aug 2026 | C13: 1 Sep 2026 | D13: Change
A14: Leveraged funds | B14: =Net_EUR!C17 -> -38359 | C14: =Net_EUR!C18 -> -38173 | D14: =C14-B14 -> 186
A15: Asset manager | B15: =Net_EUR!F17 -> 261426 | C15: =Net_EUR!F18 -> 263253 | D15: =C15-B15 -> 1827
A16: Dealer | B16: =Net_EUR!I17 -> -268581 | C16: =Net_EUR!I18 -> -267578 | D16: =C16-B16 -> 1003
A17: Other reportable | B17: =Net_EUR!L17 -> 9602 | C17: =Net_EUR!L18 -> 8846 | D17: =C17-B17 -> -756
A18: Nonreportable | B18: =Net_EUR!O17 -> 35912 | C18: =Net_EUR!O18 -> 33652 | D18: =C18-B18 -> -2260
A20: Leveraged funds net position, 13 weeks 9 Jun to 1 Sep 2026 (the chart window)
A21: Lowest | B21: =MIN(Net_EUR!C6:C18) -> -65198
A22: Highest | B22: =MAX(Net_EUR!C6:C18) -> -8926
A23: Average | B23: =AVERAGE(Net_EUR!C6:C18) -> -41726.308
A24: Net now versus the low | B24: =C8-B21 -> 27025
A26: Notes
A27: Category: Leveraged Funds in the CFTC Traders in Financial Futures report. Asset managers, dealers, other reportables and nonreportables are shown for context.
A28: Net is long minus short outright positions and excludes spreading.
A29: Positions are as of Tuesday 1 Sep and were released Friday 4 Sep, so they lag. Nothing dated after 4 Sep is used.
A30: Contract: EURO FX, CME, EUR 125,000 per contract, Futures Only.

Sheet Sources
A1: Sources
A2: Source dates: CFTC positions as of Tue 1 Sep 2026, released Fri 4 Sep 2026. Accessed 19 Oct 2026.
A4: Source | B4: URL | C4: Accessed
A5: CFTC Traders in Financial Futures, Futures Only (Public Reporting Environment dataset gpe5-46if): EURO FX 099741; British pound 096742; Japanese yen 097741; Swiss franc 092741; Canadian dollar 090741; Australian dollar 232741; New Zealand dollar 112741 | B5: https://publicreporting.cftc.gov/Commitments-of-Traders/Traders-in-Financial-Futures-Futures-Only/gpe5-46if | C5: 19 Oct 2026
A6: CFTC Commitments of Traders, report definitions and trader categories | B6: https://www.cftc.gov/MarketReports/CommitmentsofTraders/index.htm | C6: 19 Oct 2026
A7: ECB press release of 11 Jun 2026, monetary policy decisions (date of the June hike marked on the chart) | B7: https://www.ecb.europa.eu/press/pr/date/2026/html/ecb.mp260611~4d41bd5e83.en.html | C7: 19 Oct 2026
A10: Independent portfolio project built from public data. Not investment advice.
