Workbook

Sheet Raw_TFF
A1: Raw CFTC data, euro FX futures, positions as of each Tuesday
A2: Source: CFTC Public Reporting Environment, Traders in Financial Futures, Futures Only, EURO FX - CHICAGO MERCANTILE EXCHANGE (code 099741, contract of EUR 125,000). https://publicreporting.cftc.gov/Commitments-of-Traders/Traders-in-Financial-Futures-Futures-Only/gpe5-46if . Accessed 19 Oct 2026.
A3: Blue = value copied from the CFTC file. Long and short are outright positions; spreading positions are not included. Nonreportable entries for 16 Jun and 15 Sep are as published and look unusual; they are not used in the chart.
A4: Positions as of (Tuesday) | B4: Open interest | C4: Dealer long | D4: Dealer short | E4: Asset manager long | F4: Asset manager short | G4: Leveraged funds long | H4: Leveraged funds short | I4: Other reportable long | J4: Other reportable short | K4: Nonreportable long | L4: Nonreportable short
A5: 46168 | B5: 824224 | C5: 46277 | D5: 368386 | E5: 439116 | F5: 169226 | G5: 110985 | H5: 103689 | I5: 24395 | J5: 15570 | K5: 88813 | L5: 52715
A6: 46175 | B6: 842424 | C6: 45480 | D6: 374951 | E6: 454078 | F6: 168157 | G6: 109583 | H6: 97556 | I6: 25388 | J6: 14395 | K6: 86539 | L6: 66009
A7: 46182 | B7: 871507 | C7: 67752 | D7: 367097 | E7: 462310 | F7: 180754 | G7: 91856 | H7: 109244 | I7: 25497 | J7: 14473 | K7: 90399 | L7: 66246
A8: 46189 | B8: 894671 | C8: 32449 | D8: 331417 | E8: 460022 | F8: 189678 | G8: 94228 | H8: 103154 | I8: 23796 | J8: 13782 | K8: 214087 | L8: 186551
A9: 46196 | B9: 785477 | C9: 36965 | D9: 312295 | E9: 462293 | F9: 207563 | G9: 108150 | H9: 123560 | I9: 22501 | J9: 13516 | K9: 81337 | L9: 54312
A10: 46203 | B10: 790076 | C10: 39903 | D10: 293368 | E10: 470602 | F10: 215444 | G10: 102267 | H10: 134911 | I10: 20919 | J10: 13548 | K10: 80468 | L10: 56888
A11: 46210 | B11: 794833 | C11: 43012 | D11: 289135 | E11: 478070 | F11: 224152 | G11: 87460 | H11: 132921 | I11: 22853 | J11: 11438 | K11: 83533 | L11: 57282
A12: 46217 | B12: 799495 | C12: 45006 | D12: 277174 | E12: 466709 | F12: 219393 | G12: 89976 | H12: 143667 | I12: 23465 | J12: 10917 | K12: 82849 | L12: 56854
A13: 46224 | B13: 800061 | C13: 51686 | D13: 259905 | E13: 458394 | F13: 229467 | G13: 91110 | H13: 147781 | I13: 23901 | J13: 11301 | K13: 80473 | L13: 57110
A14: 46231 | B14: 819806 | C14: 76674 | D14: 252190 | E14: 449191 | F14: 239865 | G14: 92672 | H14: 157870 | I14: 23041 | J14: 12386 | K14: 78549 | L14: 57816
A15: 46238 | B15: 799909 | C15: 51250 | D15: 255728 | E15: 445903 | F15: 226641 | G15: 95389 | H15: 147594 | I15: 22715 | J15: 11923 | K15: 80953 | L15: 54324
A16: 46245 | B16: 801884 | C16: 53721 | D16: 259757 | E16: 450831 | F16: 225442 | G16: 86753 | H16: 147353 | I16: 23277 | J16: 12837 | K16: 82886 | L16: 52079
... A21: 46280 | B21: 920035 | C21: 41113 | D21: 299193 | E21: 486435 | F21: 234737 | G21: 103260 | H21: 131416 | I21: 24818 | J21: 17063 | K21: 188399 | L21: 161616

Sheet Net_Positions
A1: Net position by trader category (long minus short), week on week change, and net as % of open interest
A2: Source: CFTC Public Reporting Environment, Traders in Financial Futures, Futures Only, EURO FX - CHICAGO MERCANTILE EXCHANGE (code 099741, contract of EUR 125,000). https://publicreporting.cftc.gov/Commitments-of-Traders/Traders-in-Financial-Futures-Futures-Only/gpe5-46if . Accessed 19 Oct 2026.
A3: All cells are formulas on Raw_TFF. Net = long minus short. WoW = change from the previous Tuesday. Net % OI = net divided by open interest. Highlighted rows: 8 Sep is the last print before the 10 Sep ECB decision, 15 Sep is the first print after it.
A4: Positions as of (Tuesday) | B4: Open interest | C4: Dealer net | D4: Dealer net WoW | E4: Dealer net % OI | F4: Asset manager net | G4: Asset manager net WoW | H4: Asset manager net % OI | I4: Leveraged funds net | J4: Leveraged funds net WoW | K4: Leveraged funds net % OI | L4: Other reportable net | M4: Other reportable net WoW | N4: Other reportable net % OI | O4: Nonreportable net | P4: Nonreportable net WoW | Q4: Nonreportable net % OI
A5: =Raw_TFF!A5 | B5: =Raw_TFF!B5 | C5: =Raw_TFF!C5-Raw_TFF!D5 | D5: n/a | E5: =C5/B5 | F5: =Raw_TFF!E5-Raw_TFF!F5 | G5: n/a | H5: =F5/B5 | I5: =Raw_TFF!G5-Raw_TFF!H5 | J5: n/a | K5: =I5/B5 | L5: =Raw_TFF!I5-Raw_TFF!J5 | M5: n/a | N5: =L5/B5 | O5: =Raw_TFF!K5-Raw_TFF!L5 | P5: n/a | Q5: =O5/B5
A6: =Raw_TFF!A6 | B6: =Raw_TFF!B6 | C6: =Raw_TFF!C6-Raw_TFF!D6 | D6: =C6-C5 | E6: =C6/B6 | F6: =Raw_TFF!E6-Raw_TFF!F6 | G6: =F6-F5 | H6: =F6/B6 | I6: =Raw_TFF!G6-Raw_TFF!H6 | J6: =I6-I5 | K6: =I6/B6 | L6: =Raw_TFF!I6-Raw_TFF!J6 | M6: =L6-L5 | N6: =L6/B6 | O6: =Raw_TFF!K6-Raw_TFF!L6 | P6: =O6-O5 | Q6: =O6/B6
A7: =Raw_TFF!A7 | B7: =Raw_TFF!B7 | C7: =Raw_TFF!C7-Raw_TFF!D7 | D7: =C7-C6 | E7: =C7/B7 | F7: =Raw_TFF!E7-Raw_TFF!F7 | G7: =F7-F6 | H7: =F7/B7 | I7: =Raw_TFF!G7-Raw_TFF!H7 | J7: =I7-I6 | K7: =I7/B7 | L7: =Raw_TFF!I7-Raw_TFF!J7 | M7: =L7-L6 | N7: =L7/B7 | O7: =Raw_TFF!K7-Raw_TFF!L7 | P7: =O7-O6 | Q7: =O7/B7
A8: =Raw_TFF!A8 | B8: =Raw_TFF!B8 | C8: =Raw_TFF!C8-Raw_TFF!D8 | D8: =C8-C7 | E8: =C8/B8 | F8: =Raw_TFF!E8-Raw_TFF!F8 | G8: =F8-F7 | H8: =F8/B8 | I8: =Raw_TFF!G8-Raw_TFF!H8 | J8: =I8-I7 | K8: =I8/B8 | L8: =Raw_TFF!I8-Raw_TFF!J8 | M8: =L8-L7 | N8: =L8/B8 | O8: =Raw_TFF!K8-Raw_TFF!L8 | P8: =O8-O7 | Q8: =O8/B8
A9: =Raw_TFF!A9 | B9: =Raw_TFF!B9 | C9: =Raw_TFF!C9-Raw_TFF!D9 | D9: =C9-C8 | E9: =C9/B9 | F9: =Raw_TFF!E9-Raw_TFF!F9 | G9: =F9-F8 | H9: =F9/B9 | I9: =Raw_TFF!G9-Raw_TFF!H9 | J9: =I9-I8 | K9: =I9/B9 | L9: =Raw_TFF!I9-Raw_TFF!J9 | M9: =L9-L8 | N9: =L9/B9 | O9: =Raw_TFF!K9-Raw_TFF!L9 | P9: =O9-O8 | Q9: =O9/B9
A10: =Raw_TFF!A10 | B10: =Raw_TFF!B10 | C10: =Raw_TFF!C10-Raw_TFF!D10 | D10: =C10-C9 | E10: =C10/B10 | F10: =Raw_TFF!E10-Raw_TFF!F10 | G10: =F10-F9 | H10: =F10/B10 | I10: =Raw_TFF!G10-Raw_TFF!H10 | J10: =I10-I9 | K10: =I10/B10 | L10: =Raw_TFF!I10-Raw_TFF!J10 | M10: =L10-L9 | N10: =L10/B10 | O10: =Raw_TFF!K10-Raw_TFF!L10 | P10: =O10-O9 | Q10: =O10/B10
A11: =Raw_TFF!A11 | B11: =Raw_TFF!B11 | C11: =Raw_TFF!C11-Raw_TFF!D11 | D11: =C11-C10 | E11: =C11/B11 | F11: =Raw_TFF!E11-Raw_TFF!F11 | G11: =F11-F10 | H11: =F11/B11 | I11: =Raw_TFF!G11-Raw_TFF!H11 | J11: =I11-I10 | K11: =I11/B11 | L11: =Raw_TFF!I11-Raw_TFF!J11 | M11: =L11-L10 | N11: =L11/B11 | O11: =Raw_TFF!K11-Raw_TFF!L11 | P11: =O11-O10 | Q11: =O11/B11
A12: =Raw_TFF!A12 | B12: =Raw_TFF!B12 | C12: =Raw_TFF!C12-Raw_TFF!D12 | D12: =C12-C11 | E12: =C12/B12 | F12: =Raw_TFF!E12-Raw_TFF!F12 | G12: =F12-F11 | H12: =F12/B12 | I12: =Raw_TFF!G12-Raw_TFF!H12 | J12: =I12-I11 | K12: =I12/B12 | L12: =Raw_TFF!I12-Raw_TFF!J12 | M12: =L12-L11 | N12: =L12/B12 | O12: =Raw_TFF!K12-Raw_TFF!L12 | P12: =O12-O11 | Q12: =O12/B12
A13: =Raw_TFF!A13 | B13: =Raw_TFF!B13 | C13: =Raw_TFF!C13-Raw_TFF!D13 | D13: =C13-C12 | E13: =C13/B13 | F13: =Raw_TFF!E13-Raw_TFF!F13 | G13: =F13-F12 | H13: =F13/B13 | I13: =Raw_TFF!G13-Raw_TFF!H13 | J13: =I13-I12 | K13: =I13/B13 | L13: =Raw_TFF!I13-Raw_TFF!J13 | M13: =L13-L12 | N13: =L13/B13 | O13: =Raw_TFF!K13-Raw_TFF!L13 | P13: =O13-O12 | Q13: =O13/B13
A14: =Raw_TFF!A14 | B14: =Raw_TFF!B14 | C14: =Raw_TFF!C14-Raw_TFF!D14 | D14: =C14-C13 | E14: =C14/B14 | F14: =Raw_TFF!E14-Raw_TFF!F14 | G14: =F14-F13 | H14: =F14/B14 | I14: =Raw_TFF!G14-Raw_TFF!H14 | J14: =I14-I13 | K14: =I14/B14 | L14: =Raw_TFF!I14-Raw_TFF!J14 | M14: =L14-L13 | N14: =L14/B14 | O14: =Raw_TFF!K14-Raw_TFF!L14 | P14: =O14-O13 | Q14: =O14/B14
A15: =Raw_TFF!A15 | B15: =Raw_TFF!B15 | C15: =Raw_TFF!C15-Raw_TFF!D15 | D15: =C15-C14 | E15: =C15/B15 | F15: =Raw_TFF!E15-Raw_TFF!F15 | G15: =F15-F14 | H15: =F15/B15 | I15: =Raw_TFF!G15-Raw_TFF!H15 | J15: =I15-I14 | K15: =I15/B15 | L15: =Raw_TFF!I15-Raw_TFF!J15 | M15: =L15-L14 | N15: =L15/B15 | O15: =Raw_TFF!K15-Raw_TFF!L15 | P15: =O15-O14 | Q15: =O15/B15
A16: =Raw_TFF!A16 | B16: =Raw_TFF!B16 | C16: =Raw_TFF!C16-Raw_TFF!D16 | D16: =C16-C15 | E16: =C16/B16 | F16: =Raw_TFF!E16-Raw_TFF!F16 | G16: =F16-F15 | H16: =F16/B16 | I16: =Raw_TFF!G16-Raw_TFF!H16 | J16: =I16-I15 | K16: =I16/B16 | L16: =Raw_TFF!I16-Raw_TFF!J16 | M16: =L16-L15 | N16: =L16/B16 | O16: =Raw_TFF!K16-Raw_TFF!L16 | P16: =O16-O15 | Q16: =O16/B16
A17: =Raw_TFF!A17 | B17: =Raw_TFF!B17 | C17: =Raw_TFF!C17-Raw_TFF!D17 | D17: =C17-C16 | E17: =C17/B17 | F17: =Raw_TFF!E17-Raw_TFF!F17 | G17: =F17-F16 | H17: =F17/B17 | I17: =Raw_TFF!G17-Raw_TFF!H17 | J17: =I17-I16 | K17: =I17/B17 | L17: =Raw_TFF!I17-Raw_TFF!J17 | M17: =L17-L16 | N17: =L17/B17 | O17: =Raw_TFF!K17-Raw_TFF!L17 | P17: =O17-O16 | Q17: =O17/B17
... A21: =Raw_TFF!A21 | B21: =Raw_TFF!B21 | C21: =Raw_TFF!C21-Raw_TFF!D21 | D21: =C21-C20 | E21: =C21/B21 | F21: =Raw_TFF!E21-Raw_TFF!F21 | G21: =F21-F20 | H21: =F21/B21 | I21: =Raw_TFF!G21-Raw_TFF!H21 | J21: =I21-I20 | K21: =I21/B21 | L21: =Raw_TFF!I21-Raw_TFF!J21 | M21: =L21-L20 | N21: =L21/B21 | O21: =Raw_TFF!K21-Raw_TFF!L21 | P21: =O21-O20 | Q21: =O21/B21

Sheet Summary
A1: Summary: leveraged funds in euro FX futures, 1 to 15 Sep 2026 (report of 18 Sep 2026)
A2: Source: CFTC Public Reporting Environment, Traders in Financial Futures, Futures Only, EURO FX - CHICAGO MERCANTILE EXCHANGE (code 099741, contract of EUR 125,000). https://publicreporting.cftc.gov/Commitments-of-Traders/Traders-in-Financial-Futures-Futures-Only/gpe5-46if . Accessed 19 Oct 2026.
A3: The 8 Sep print was taken two days before the 10 Sep decision; the 15 Sep print is the first one after it. All cells are formulas on Net_Positions and Raw_TFF.
A5: Leveraged funds | B5: 1 Sep 2026 | C5: 8 Sep 2026 (last before decision) | D5: 15 Sep 2026 (first after decision) | E5: Change 1 to 8 Sep | F5: Change 8 to 15 Sep
A6: Long contracts | B6: =Raw_TFF!G19 | C6: =Raw_TFF!G20 | D6: =Raw_TFF!G21 | E6: =C6-B6 | F6: =D6-C6
A7: Short contracts | B7: =Raw_TFF!H19 | C7: =Raw_TFF!H20 | D7: =Raw_TFF!H21 | E7: =C7-B7 | F7: =D7-C7
A8: Net position | B8: =Net_Positions!I19 | C8: =Net_Positions!I20 | D8: =Net_Positions!I21 | E8: =C8-B8 | F8: =D8-C8
A9: Open interest | B9: =Raw_TFF!B19 | C9: =Raw_TFF!B20 | D9: =Raw_TFF!B21 | E9: =C9-B9 | F9: =D9-C9
A10: Net % of open interest | B10: =Net_Positions!K19 | C10: =Net_Positions!K20 | D10: =Net_Positions!K21 | E10: =C10-B10 | F10: =D10-C10
A12: Net position by category
A13: Category | B13: 1 Sep 2026 | C13: 8 Sep 2026 (last before decision) | D13: 15 Sep 2026 (first after decision) | E13: Change 1 to 8 Sep | F13: Change 8 to 15 Sep
A14: Dealer | B14: =Net_Positions!C19 | C14: =Net_Positions!C20 | D14: =Net_Positions!C21 | E14: =C14-B14 | F14: =D14-C14
A15: Asset manager | B15: =Net_Positions!F19 | C15: =Net_Positions!F20 | D15: =Net_Positions!F21 | E15: =C15-B15 | F15: =D15-C15
A16: Leveraged funds | B16: =Net_Positions!I19 | C16: =Net_Positions!I20 | D16: =Net_Positions!I21 | E16: =C16-B16 | F16: =D16-C16
A17: Other reportable | B17: =Net_Positions!L19 | C17: =Net_Positions!L20 | D17: =Net_Positions!L21 | E17: =C17-B17 | F17: =D17-C17
A18: Nonreportable | B18: =Net_Positions!O19 | C18: =Net_Positions!O20 | D18: =Net_Positions!O21 | E18: =C18-B18 | F18: =D18-C18
A20: Leveraged funds net position, 14 weeks 16 Jun to 15 Sep 2026 (the chart window)
A21: Lowest | B21: =MIN(Net_Positions!I8:I21)
A22: Highest | B22: =MAX(Net_Positions!I8:I21)
A23: Average | B23: =AVERAGE(Net_Positions!I8:I21)
A25: Notes
A26: Category: Leveraged Funds in the CFTC Traders in Financial Futures report (hedge funds and other leveraged accounts). Asset managers, dealers, other reportables and nonreportables are shown for context.
A27: Net is long minus short outright positions and excludes spreading, the same convention as the CFTC's net figures.
A28: Positions are as of Tuesday and published the following Friday. The 15 Sep print falls in the quarterly contract roll week, when open interest moves for reasons unrelated to the decision.
A29: Contract: EURO FX, CME, EUR 125,000 per contract, Futures Only.

Sheet Sources
A1: Sources
A3: Source | B3: URL | C3: Accessed
A4: CFTC Traders in Financial Futures, Futures Only, EURO FX (Public Reporting Environment dataset gpe5-46if) | B4: https://publicreporting.cftc.gov/Commitments-of-Traders/Traders-in-Financial-Futures-Futures-Only/gpe5-46if | C4: 19 Oct 2026
A5: CFTC Commitments of Traders landing page (report definitions and categories) | B5: https://www.cftc.gov/MarketReports/CommitmentsofTraders/index.htm | C5: 19 Oct 2026
A6: CFTC 2026 release schedule (15 Sep positions released Fri 18 Sep 2026, 3:30 p.m. ET) | B6: https://www.cftc.gov/MarketReports/CommitmentsofTraders/ReleaseSchedule/index.htm | C6: 21 Oct 2026
A9: Independent portfolio project built from public data. Not investment advice.
